{
  "ocel:global-event": {
    "ocel:activity": [
      "remove item",
      "item out of stock",
      "pack item",
      "add item to package",
      "select item",
      "pay item"
    ]
  },
  "ocel:global-object": {
    "ocel:type": "__INVALID__"
  },
  "ocel:global-log": {
    "ocel:attribute-names": [
      "WEIGHT",
      "PACKAGENUMBER",
      "PRICE",
      "ORDERNUMBER"
    ],
    "ocel:object-types": [
      "CASE_ITEMS",
      "CASE_PACKAGES"
    ],
    "ocel:version": "1.0",
    "ocel:ordering": "timestamp"
  },
  "ocel:events": {
    "0": {
      "ocel:activity": "select item",
      "ocel:timestamp": "2020-07-15 12:54:00",
      "ocel:omap": [
        "i3"
      ],
      "ocel:vmap": {
        "PACKAGENUMBER": "p1",
        "PRICE": 3,
        "WEIGHT": 40
      }
    },
    "1": {
      "ocel:activity": "remove item",
      "ocel:timestamp": "2020-07-15 12:55:00",
      "ocel:omap": [
        "i3"
      ],
      "ocel:vmap": {
        "PACKAGENUMBER": "p1",
        "PRICE": 3,
        "WEIGHT": 40
      }
    },
    "2": {
      "ocel:activity": "select item",
      "ocel:timestamp": "2020-07-15 13:00:00",
      "ocel:omap": [
        "i1"
      ],
      "ocel:vmap": {
        "PACKAGENUMBER": "p1",
        "PRICE": 10,
        "WEIGHT": 300
      }
    },
    "3": {
      "ocel:activity": "select item",
      "ocel:timestamp": "2020-07-15 13:00:00",
      "ocel:omap": [
        "i2"
      ],
      "ocel:vmap": {
        "PACKAGENUMBER": "p1",
        "PRICE": 15,
        "WEIGHT": 210
      }
    },
    "4": {
      "ocel:activity": "select item",
      "ocel:timestamp": "2020-07-15 13:00:00",
      "ocel:omap": [
        "i3"
      ],
      "ocel:vmap": {
        "PACKAGENUMBER": "p1",
        "PRICE": 3,
        "WEIGHT": 40
      }
    },
    "5": {
      "ocel:activity": "pack item",
      "ocel:timestamp": "2020-07-15 14:00:00",
      "ocel:omap": [
        "i1"
      ],
      "ocel:vmap": {
        "PACKAGENUMBER": "p1",
        "PRICE": 10,
        "WEIGHT": 300
      }
    },
    "6": {
      "ocel:activity": "pack item",
      "ocel:timestamp": "2020-07-15 14:00:00",
      "ocel:omap": [
        "i2"
      ],
      "ocel:vmap": {
        "PACKAGENUMBER": "p1",
        "PRICE": 15,
        "WEIGHT": 210
      }
    },
    "7": {
      "ocel:activity": "pack item",
      "ocel:timestamp": "2020-07-15 14:00:00",
      "ocel:omap": [
        "i3"
      ],
      "ocel:vmap": {
        "PACKAGENUMBER": "p1",
        "PRICE": 3,
        "WEIGHT": 40
      }
    },
    "8": {
      "ocel:activity": "add item to package",
      "ocel:timestamp": "2020-07-15 14:10:00",
      "ocel:omap": [
        "p1",
        "i1"
      ],
      "ocel:vmap": {
        "PACKAGENUMBER": "p1",
        "PRICE": 10,
        "WEIGHT": 300,
        "ORDERNUMBER": "o1"
      }
    },
    "9": {
      "ocel:activity": "add item to package",
      "ocel:timestamp": "2020-07-15 14:10:00",
      "ocel:omap": [
        "p1",
        "i3"
      ],
      "ocel:vmap": {
        "PACKAGENUMBER": "p1",
        "PRICE": 3,
        "WEIGHT": 40,
        "ORDERNUMBER": "o1"
      }
    },
    "10": {
      "ocel:activity": "add item to package",
      "ocel:timestamp": "2020-07-15 14:10:00",
      "ocel:omap": [
        "i2",
        "p1"
      ],
      "ocel:vmap": {
        "PACKAGENUMBER": "p1",
        "PRICE": 15,
        "WEIGHT": 210,
        "ORDERNUMBER": "o1"
      }
    },
    "11": {
      "ocel:activity": "pay item",
      "ocel:timestamp": "2020-07-15 14:30:00",
      "ocel:omap": [
        "i3"
      ],
      "ocel:vmap": {
        "PACKAGENUMBER": "p1",
        "PRICE": 3,
        "WEIGHT": 40
      }
    },
    "12": {
      "ocel:activity": "pay item",
      "ocel:timestamp": "2020-07-15 14:30:00",
      "ocel:omap": [
        "i1"
      ],
      "ocel:vmap": {
        "PACKAGENUMBER": "p1",
        "PRICE": 10,
        "WEIGHT": 300
      }
    },
    "13": {
      "ocel:activity": "pay item",
      "ocel:timestamp": "2020-07-15 14:30:00",
      "ocel:omap": [
        "i2"
      ],
      "ocel:vmap": {
        "PACKAGENUMBER": "p1",
        "PRICE": 15,
        "WEIGHT": 210
      }
    },
    "14": {
      "ocel:activity": "select item",
      "ocel:timestamp": "2020-07-16 09:21:00",
      "ocel:omap": [
        "i4"
      ],
      "ocel:vmap": {
        "PACKAGENUMBER": "p2",
        "PRICE": 16,
        "WEIGHT": 1200
      }
    },
    "15": {
      "ocel:activity": "item out of stock",
      "ocel:timestamp": "2020-07-16 10:12:00",
      "ocel:omap": [
        "i4"
      ],
      "ocel:vmap": {
        "PACKAGENUMBER": "p2",
        "PRICE": 16,
        "WEIGHT": 1200
      }
    },
    "16": {
      "ocel:activity": "select item",
      "ocel:timestamp": "2020-07-20 10:29:00",
      "ocel:omap": [
        "i5"
      ],
      "ocel:vmap": {
        "PACKAGENUMBER": "p2",
        "PRICE": 230,
        "WEIGHT": 950
      }
    },
    "17": {
      "ocel:activity": "pack item",
      "ocel:timestamp": "2020-07-20 10:30:00",
      "ocel:omap": [
        "i4"
      ],
      "ocel:vmap": {
        "PACKAGENUMBER": "p2",
        "PRICE": 16,
        "WEIGHT": 1200
      }
    },
    "18": {
      "ocel:activity": "pack item",
      "ocel:timestamp": "2020-07-20 10:30:00",
      "ocel:omap": [
        "i5"
      ],
      "ocel:vmap": {
        "PACKAGENUMBER": "p2",
        "PRICE": 230,
        "WEIGHT": 950
      }
    },
    "19": {
      "ocel:activity": "add item to package",
      "ocel:timestamp": "2020-07-20 10:31:00",
      "ocel:omap": [
        "i4",
        "p2"
      ],
      "ocel:vmap": {
        "PACKAGENUMBER": "p2",
        "PRICE": 16,
        "WEIGHT": 1200,
        "ORDERNUMBER": "o2"
      }
    },
    "20": {
      "ocel:activity": "add item to package",
      "ocel:timestamp": "2020-07-20 10:31:00",
      "ocel:omap": [
        "i5",
        "p2"
      ],
      "ocel:vmap": {
        "PACKAGENUMBER": "p2",
        "PRICE": 230,
        "WEIGHT": 950,
        "ORDERNUMBER": "o2"
      }
    },
    "21": {
      "ocel:activity": "pay item",
      "ocel:timestamp": "2020-07-20 12:44:20",
      "ocel:omap": [
        "i4"
      ],
      "ocel:vmap": {
        "PACKAGENUMBER": "p2",
        "PRICE": 16,
        "WEIGHT": 1200
      }
    },
    "22": {
      "ocel:activity": "pay item",
      "ocel:timestamp": "2020-07-20 12:44:20",
      "ocel:omap": [
        "i5"
      ],
      "ocel:vmap": {
        "PACKAGENUMBER": "p2",
        "PRICE": 230,
        "WEIGHT": 950
      }
    },
    "23": {
      "ocel:activity": "select item",
      "ocel:timestamp": "2020-07-20 17:20:00",
      "ocel:omap": [
        "i6"
      ],
      "ocel:vmap": {
        "PACKAGENUMBER": "p3",
        "PRICE": 70,
        "WEIGHT": 330
      }
    },
    "24": {
      "ocel:activity": "pay item",
      "ocel:timestamp": "2020-07-20 17:20:33",
      "ocel:omap": [
        "i6"
      ],
      "ocel:vmap": {
        "PACKAGENUMBER": "p3",
        "PRICE": 70,
        "WEIGHT": 330
      }
    },
    "25": {
      "ocel:activity": "pack item",
      "ocel:timestamp": "2020-07-20 17:22:10",
      "ocel:omap": [
        "i6"
      ],
      "ocel:vmap": {
        "PACKAGENUMBER": "p3",
        "PRICE": 70,
        "WEIGHT": 330
      }
    },
    "26": {
      "ocel:activity": "add item to package",
      "ocel:timestamp": "2020-07-20 17:24:00",
      "ocel:omap": [
        "i6",
        "p3"
      ],
      "ocel:vmap": {
        "PACKAGENUMBER": "p3",
        "PRICE": 70,
        "WEIGHT": 330,
        "ORDERNUMBER": "o2"
      }
    }
  },
  "ocel:objects": {
    "i1": {
      "ocel:type": "CASE_ITEMS",
      "ocel:ovmap": {}
    },
    "i2": {
      "ocel:type": "CASE_ITEMS",
      "ocel:ovmap": {}
    },
    "i3": {
      "ocel:type": "CASE_ITEMS",
      "ocel:ovmap": {}
    },
    "i4": {
      "ocel:type": "CASE_ITEMS",
      "ocel:ovmap": {}
    },
    "i5": {
      "ocel:type": "CASE_ITEMS",
      "ocel:ovmap": {}
    },
    "i6": {
      "ocel:type": "CASE_ITEMS",
      "ocel:ovmap": {}
    },
    "p1": {
      "ocel:type": "CASE_PACKAGES",
      "ocel:ovmap": {}
    },
    "p2": {
      "ocel:type": "CASE_PACKAGES",
      "ocel:ovmap": {}
    },
    "p3": {
      "ocel:type": "CASE_PACKAGES",
      "ocel:ovmap": {}
    }
  }
}